rpi_led/__init__.py
rpi_led-0.1.0.dist-info/METADATA
rpi_led-0.1.0.dist-info/WHEEL
rpi_led-0.1.0.dist-info/top_level.txt
rpi_led-0.1.0.dist-info/RECORD
