Metadata-Version: 2.4
Name: rpi-led
Version: 0.1.0
Summary: A simple library to control builtin LED on a Raspberry Pi
Author-email: TrRuki <TrRuki.mail@gmail.com>
License: MIT
Requires-Python: >=3.8
